grafilter/__init__.py
grafilter/background.py
grafilter/cache.py
grafilter/cli.py
grafilter/flask.py
grafilter/influxdb.py
grafilter/utils.py
grafilter/static/favicon.ico
grafilter/static/index.js
grafilter/templates/base.html
grafilter/templates/index.html
grafilter/templates/metric.html
grafilter-0.4.0.dist-info/DESCRIPTION.rst
grafilter-0.4.0.dist-info/entry_points.txt
grafilter-0.4.0.dist-info/METADATA
grafilter-0.4.0.dist-info/metadata.json
grafilter-0.4.0.dist-info/RECORD
grafilter-0.4.0.dist-info/top_level.txt
grafilter-0.4.0.dist-info/WHEEL
